fiqci/ems/__init__.py
fiqci/ems/fiqci_backend.py
fiqci/ems/rem.py
fiqci/ems/utils.py
fiqci_ems-0.1.0.dist-info/licenses/LICENSE
fiqci_ems-0.1.0.dist-info/METADATA
fiqci_ems-0.1.0.dist-info/WHEEL
fiqci_ems-0.1.0.dist-info/top_level.txt
fiqci_ems-0.1.0.dist-info/RECORD
