Metadata-Version: 2.4
Name: fiqci-ems
Version: 0.1.0
Summary: FiQCI Error Mitigation Service
Author-email: FiQCI <servicedesk@csc.fi>
Maintainer-email: FiQCI <servicedesk@csc.fi>
License: Apache-2.0
Project-URL: Homepage, https://github.com/fiqci/fiqci-ems
Project-URL: Repository, https://github.com/fiqci/fiqci-ems
Project-URL: Issues, https://github.com/fiqci/fiqci-ems/issues
Project-URL: Changelog, https://github.com/fiqci/fiqci-ems/blob/main/CHANGELOG.md
Keywords: quantum computing,error mitigation,quantum error correction,FiQCI,readout error mitigation
Classifier: Development Status :: 3 - Alpha
Classifier: Intended Audience :: Science/Research
Classifier: Intended Audience :: Developers
Classifier: License :: OSI Approved :: Apache Software License
Classifier: Programming Language :: Python :: 3
Classifier: Programming Language :: Python :: 3.11
Classifier: Topic :: Scientific/Engineering :: Physics
Classifier: Topic :: Software Development :: Libraries :: Python Modules
Requires-Python: <3.12,>=3.11
License-File: LICENSE
Requires-Dist: iqm-client[qiskit]==33.0.0
Requires-Dist: matplotlib>=3.10.7
Requires-Dist: mthree>=3.0.0
Provides-Extra: docs
Requires-Dist: ipykernel>=7.1.0; extra == "docs"
Requires-Dist: ipywidgets>=8.1.8; extra == "docs"
Requires-Dist: pylatexenc>=2.10; extra == "docs"
Dynamic: license-file
